[
    {
        "_id": "c1d475f2-05c0-4965-af65-9bd716942999",
        "created_at": "2021-12-03 15:33:37.247073",
        "isActive": true,
        "isArchived": false,
        "isOpen": true,
        "isFinished": false,
        "isClosed": false,
        "Address": {
            "country": "Iceland",
            "city": "Reykjavik",
            "zip": "101",
            "address1": "Bankastr\u00e6ti 5",
            "address2": null,
            "address3": null
        },
        "to_do": [
            "Bor\u00f0a mat",
            "sl\u00e1 vegg",
            "kaupa b\u00edl"
        ],
        "isRegular": true,
        "occurance": "ha",
        "priority": "HIGH",
        "start_date": "now",
        "employeeId": "37a229db-6157-4bbe-b898-9d2abafb464d",
        "verification_number": "VB00001"
    },
    {
        "_id": "1faed923-f5f1-4a2f-9f98-ae8040746f89",
        "created_at": "2021-12-03 16:01:11.521074",
        "isActive": true,
        "isArchived": false,
        "isOpen": true,
        "isFinished": false,
        "isClosed": false,
        "Address": {
            "country": "Iceland",
            "city": "Reykjavik",
            "zip": "101",
            "address1": "Prikah\u00fas 2",
            "address2": null,
            "address3": null
        },
        "to_do": [
            "Bor\u00f0a mat",
            "kaupa t\u00f6lvu",
            "selja hj\u00f3l"
        ],
        "isRegular": true,
        "occurance": "ha",
        "priority": "HIGH",
        "start_date": "now",
        "employeeId": "37a229db-6157-4bbe-b898-9d2abafb464d",
        "verification_number": "VB00002"
    },
    {
        "_id": "1ae343f7-4b27-469b-88c9-92bcd293f6df",
        "created_at": "2021-12-03 16:01:18.224285",
        "isActive": true,
        "isArchived": false,
        "isOpen": true,
        "isFinished": false,
        "isClosed": false,
        "Address": {
            "country": "Iceland",
            "city": "Reykjavik",
            "zip": "101",
            "address1": "Prikah\u00fas 2",
            "address2": null,
            "address3": null
        },
        "to_do": [
            "Bor\u00f0a mat",
            "kaupa t\u00f6lvu",
            "selja hj\u00f3l"
        ],
        "isRegular": true,
        "occurance": "ha",
        "priority": "HIGH",
        "start_date": "now",
        "employeeId": "37a229db-6157-4bbe-b898-9d2abafb464d",
        "verification_number": "VB00003"
    },
    {
        "_id": "6007e8e4-3e77-47a1-a9a2-c855cff8475f",
        "created_at": "2021-12-06 17:53:29.036064",
        "isActive": true,
        "isArchived": false,
        "status": {
            "status": ""
        },
        "Address": "sdf",
        "to_do": [
            "3",
            ""
        ],
        "isRegular": true,
        "occurance": 1,
        "priority": "A",
        "start_date": 1638813209,
        "employeeId": null,
        "verification_number": "VB00004"
    },
    {
        "_id": "8ed48fd6-3d04-428a-be9c-41350c8f3e2e",
        "created_at": "2021-12-07 16:42:55.508473",
        "isActive": true,
        "isArchived": false,
        "status": {
            "status": ""
        },
        "property": {
            "_id": "5cdcc5ab-a8fd-4206-866c-34d76d84242b",
            "created_at": "2021-12-07 02:40:35.445155",
            "isActive": true,
            "isArchived": false,
            "Address": {
                "country": "Greenland",
                "city": "Nuuk",
                "zip": "9902",
                "address1": "Longearbyen 1",
                "address2": "",
                "address3": ""
            },
            "propertyId": "PP8000",
            "amenities": [
                "Toilet",
                "Kitchen",
                "Airport",
                ""
            ],
            "employees": [
                "2a183d14-41e5-49f0-bbca-fcf19028a130",
                "0068302d-fcf5-429c-9d01-1655ed6ce816",
                "e6f25e0b-659c-434e-9261-e251a87d4ed9",
                "0c53e3c4-090d-4d6e-8449-39de2c170e1b"
            ],
            "Rooms": [
                {
                    "size": 30.0,
                    "roomId": "PP8000"
                },
                {
                    "size": 50.0,
                    "roomId": "room2"
                }
            ]
        },
        "to_do": [
            "clean window",
            "empty pool",
            ""
        ],
        "isRegular": true,
        "occurance": 12,
        "priority": "B",
        "start_date": 1638895375,
        "employeeId": null,
        "verification_number": "VB00005"
    },
    {
        "_id": "8b967d2c-29b2-42e2-8ef1-b16e37a98d3d",
        "created_at": "2021-12-07 17:52:50.439991",
        "isActive": true,
        "isArchived": false,
        "status": {
            "status": ""
        },
        "property_id": "PP8000",
        "to_do": [
            ""
        ],
        "isRegular": false,
        "occurance": false,
        "priority": "C",
        "start_date": 1638899570,
        "employeeId": null,
        "verification_number": "VB00006"
    },
    {
        "_id": "34c1af80-4bd7-4f5a-ac2c-c69becf26975",
        "created_at": "2021-12-08 18:00:01.441879",
        "isActive": true,
        "isArchived": false,
        "status": "Upcoming",
        "property_id": "PP8000",
        "to_do": [
            ""
        ],
        "isRegular": true,
        "occurance": 12,
        "priority": "A",
        "start_date": null,
        "employeeId": null,
        "verification_number": "VB00007",
        "contractor_id": null
    },
    {
        "_id": "e6342553-3d2f-47a6-b22c-4fb72898c26b",
        "created_at": "2021-12-08 18:02:19.804542",
        "isActive": true,
        "isArchived": false,
        "status": "Upcoming",
        "property_id": "PP8000",
        "to_do": [
            ""
        ],
        "isRegular": true,
        "occurance": 12,
        "priority": "A",
        "start_date": null,
        "employeeId": null,
        "verification_number": "VB00008",
        "contractor_id": null
    },
    {
        "_id": "8f508a60-7df2-455a-a36d-ecb7b0971757",
        "created_at": "2021-12-08 18:03:40.709347",
        "isActive": true,
        "isArchived": false,
        "status": "Upcoming",
        "property_id": "PP8000",
        "to_do": [
            ""
        ],
        "isRegular": true,
        "occurance": 12,
        "priority": "A",
        "start_date": null,
        "employeeId": null,
        "verification_number": "VB00009",
        "contractor_id": null
    },
    {
        "_id": "a368ec71-2160-44e9-b7c2-dc6b65106edf",
        "created_at": "2021-12-08 18:04:51.416433",
        "isActive": true,
        "isArchived": false,
        "status": "Upcoming",
        "property_id": "PP8000",
        "to_do": [
            "a",
            "a",
            ""
        ],
        "isRegular": true,
        "occurance": 12,
        "priority": "A",
        "start_date": null,
        "employeeId": null,
        "verification_number": "VB00010",
        "contractor_id": null
    }
]